README.md
setup.cfg
setup.py
bin/codeship
codeship_cli/__init__.py
codeship_cli/api.py
codeship_cli/errors.py
codeship_cli.egg-info/PKG-INFO
codeship_cli.egg-info/SOURCES.txt
codeship_cli.egg-info/dependency_links.txt
codeship_cli.egg-info/requires.txt
codeship_cli.egg-info/top_level.txt
codeship_cli/commands/__init__.py
codeship_cli/commands/codedeploy.py
codeship_cli/commands/configure.py
codeship_cli/commands/importer.py
codeship_cli/commands/info.py
codeship_cli/commands/search.py
codeship_cli/commands/show-envs.py