Metadata-Version: 1.1
Name: codeship-cli
Version: 0.0.5
Summary: Codeship client to help find text, see configurations by terminal
Home-page: https://github.com/agutoli/codeship-cli
Author: Bruno Agutoli
Author-email: bruno.agutoli@gmail.com
License: Codeship cli to manipulate projects
Download-URL: https://github.com/agutoli/codeship-cli/archive/master.zip
Keywords: codeship,ci,codedeploy
Platform: UNKNOWN
